kkpyutil.py
kkpyutil_helper/windows/kkttssave.ps1
kkpyutil_helper/windows/kkttsspeak.ps1
kkpyutil-1.50.0.dist-info/LICENSE
kkpyutil-1.50.0.dist-info/METADATA
kkpyutil-1.50.0.dist-info/WHEEL
kkpyutil-1.50.0.dist-info/RECORD
