Metadata-Version: 2.1
Name: kkpyutil
Version: 1.50.0
Summary: Building blocks for sysadmin and DevOps
Home-page: https://github.com/kakyoism/kkpyutil/
License: MIT
Keywords: utility,logging,systems
Author: Beinan Li
Author-email: li.beinan@gmail.com
Maintainer: Beinan Li
Maintainer-email: li.beinan@gmail.com
Requires-Python: >=3.9,<4.0
Classifier: License :: OSI Approved :: MIT License
Classifier: Programming Language :: Python :: 3
Classifier: Programming Language :: Python :: 3.9
Classifier: Programming Language :: Python :: 3.10
Classifier: Programming Language :: Python :: 3.11
Project-URL: Documentation, https://github.com/kakyoism/kkpyutil/README.md
Project-URL: Repository, https://github.com/kakyoism/kkpyutil/
Project-URL: issues, https://github.com/kakyoism/kkpyutil/issues
